__init__.py
_version.py
main.py
FFmpeg/__init__.py
FFmpeg/ffmpeg.py
FFmpeg/ffmpegCommandBuilder.py
ffmpeg_py-0.1.1.dist-info/LICENSE
ffmpeg_py-0.1.1.dist-info/METADATA
ffmpeg_py-0.1.1.dist-info/WHEEL
ffmpeg_py-0.1.1.dist-info/top_level.txt
ffmpeg_py-0.1.1.dist-info/RECORD
