Metadata-Version: 2.1
Name: ffmpeg-py
Version: 0.1.1
Summary: Simple Python wrapper for FFmpeg
Download-URL: http://pypi.python.org/pypi/ffmpeg-py
Author: Gautam Dhingra
Author-email: gautamdhingra8404@gmail.com
License: MIT
Project-URL: Source, https://github.com/gautam8404/ffmpeg-py
Classifier: Programming Language :: Python :: 3
Classifier: License :: OSI Approved :: MIT License
Classifier: Operating System :: OS Independent
Requires-Python: >=3.5
License-File: LICENSE
